synadb/__init__.py
synadb/cascade.py
synadb/experience.py
synadb/experiment.py
synadb/gpu.py
synadb/gwi.py
synadb/jupyter.py
synadb/libsynadb-arm64.dylib
synadb/libsynadb-x86_64.dylib
synadb/libsynadb.so
synadb/mmap_vector.py
synadb/models.py
synadb/run_ui.py
synadb/sparse_vector_store.py
synadb/studio.py
synadb/synadb.dll
synadb/tensor.py
synadb/tensorflow.py
synadb/torch.py
synadb/tpu.py
synadb/vector.py
synadb/wrapper.py
synadb/integrations/__init__.py
synadb/integrations/haystack.py
synadb/integrations/langchain.py
synadb/integrations/llamaindex.py
synadb/integrations/mlflow.py
synadb/integrations/mlflow_example.py
synadb-1.1.0.dist-info/METADATA
synadb-1.1.0.dist-info/WHEEL
synadb-1.1.0.dist-info/top_level.txt
synadb-1.1.0.dist-info/RECORD
