Metadata-Version: 2.4
Name: synadb
Version: 1.1.0
Summary: AI-native embedded database for ML/AI applications - vectors, tensors, experiments, and model registry
Home-page: https://github.com/gtava5813/SynaDB
Author: Golvis Tavarez
Author-email: gtava5813 <hello@synadb.ai>
License: SynaDB License
Project-URL: Homepage, https://synadb.ai
Project-URL: Documentation, https://github.com/gtava5813/SynaDB/wiki
Project-URL: Repository, https://github.com/gtava5813/SynaDB
Project-URL: Issues, https://github.com/gtava5813/SynaDB/issues
Keywords: database,embedded,ai,ml,machine-learning,vector-database,embeddings,rag,llm,experiment-tracking,model-registry,tensor
Classifier: Development Status :: 4 - Beta
Classifier: Intended Audience :: Developers
Classifier: Intended Audience :: Science/Research
Classifier: License :: Other/Proprietary License
Classifier: Operating System :: OS Independent
Classifier: Programming Language :: Python :: 3
Classifier: Programming Language :: Python :: 3.8
Classifier: Programming Language :: Python :: 3.9
Classifier: Programming Language :: Python :: 3.10
Classifier: Programming Language :: Python :: 3.11
Classifier: Programming Language :: Python :: 3.12
Classifier: Topic :: Database
Classifier: Topic :: Scientific/Engineering :: Artificial Intelligence
Requires-Python: >=3.8
Requires-Dist: numpy>=1.21.0
Provides-Extra: ml
Requires-Dist: torch>=2.0.0; extra == "ml"
Requires-Dist: datasets>=2.14.0; extra == "ml"
Requires-Dist: transformers>=4.30.0; extra == "ml"
Provides-Extra: pandas
Requires-Dist: pandas>=1.3.0; extra == "pandas"
Provides-Extra: dev
Requires-Dist: pytest>=7.0.0; extra == "dev"
Requires-Dist: hypothesis>=6.0.0; extra == "dev"
Requires-Dist: build; extra == "dev"
Requires-Dist: twine; extra == "dev"
Provides-Extra: all
Requires-Dist: synadb[ml,pandas]; extra == "all"
Dynamic: author
Dynamic: home-page
Dynamic: requires-python
